NeonPathPlanning/__init__.py
NeonPathPlanning/commons.py
NeonPathPlanning/limit_cycle.py
NeonPathPlanning/potential_fields.py
NeonPathPlanning/univector_field.py
NeonPathPlanning-1.0.1.dist-info/LICENSE
NeonPathPlanning-1.0.1.dist-info/METADATA
NeonPathPlanning-1.0.1.dist-info/WHEEL
NeonPathPlanning-1.0.1.dist-info/top_level.txt
NeonPathPlanning-1.0.1.dist-info/RECORD
