Metadata-Version: 2.1
Name: NeonPathPlanning
Version: 1.0.1
Summary: Collection of autonomous robot path planners
Author: Project-Neon
Author-email: projectneon@gmail.com
License: GNU
License-File: LICENSE
Requires-Dist: numpy
